fastpaste/__init__.py
fastpaste/fastpaste.py
fastpaste-0.1.3.dist-info/METADATA
fastpaste-0.1.3.dist-info/WHEEL
fastpaste-0.1.3.dist-info/top_level.txt
fastpaste-0.1.3.dist-info/RECORD
