Metadata-Version: 2.1
Name: fastpaste
Version: 0.1.3
Summary: Easy To Use Api Wrapper For PasteSite.org
Home-page: https://github.com/0xSwiftSilver/fastpaste
Author: 0xSwiftSilver
Author-email: williamgiovanna@protonmail.com
License: UNKNOWN
Project-URL: Bug Tracker, https://github.com/0xSwiftSilver/fastpaste/issues
Project-URL: Documentation, https://github.com/0xSwiftSilver/fastpaste/blob/main/README.md#documentation
Platform: UNKNOWN
Classifier: Development Status :: 3 - Alpha
Classifier: Intended Audience :: Developers
Classifier: Programming Language :: Python :: 3
Classifier: Operating System :: Unix
Classifier: Operating System :: MacOS :: MacOS X
Classifier: Operating System :: Microsoft :: Windows
Requires-Dist: pyaes
Requires-Dist: pbkdf2
Requires-Dist: requests
